obdtracker/__init__.py
obdtracker/api.py
obdtracker/api_caller.py
obdtracker/device_status.py
obdtracker/location.py
obdtracker/obd.py
obdtracker/updater.py
obdtracker/utils.py
obdtracker-0.2.6.dist-info/LICENSE
obdtracker-0.2.6.dist-info/METADATA
obdtracker-0.2.6.dist-info/WHEEL
obdtracker-0.2.6.dist-info/top_level.txt
obdtracker-0.2.6.dist-info/RECORD
