Metadata-Version: 2.1
Name: obdtracker
Version: 0.2.6
Summary: Library to read data from http://www.aika168.com and other cloud services to track cars with GPS trackers installed
Home-page: https://github.com/nyxnyx/gps_obd2_tracker
Author: Grzegorz Szostak
Author-email: szostak.grzegorz@gmail.com
License: UNKNOWN
Platform: UNKNOWN
Classifier: Programming Language :: Python :: 3
Classifier: License :: OSI Approved :: GNU General Public License v3 (GPLv3)
Classifier: Operating System :: OS Independent
Requires-Python: >=3.6
